ocrmypdf/RELEASE.md
ocrmypdf/__init__.py
ocrmypdf/__main__.py
ocrmypdf/_annots.py
ocrmypdf/_concurrent.py
ocrmypdf/_defaults.py
ocrmypdf/_graft.py
ocrmypdf/_jobcontext.py
ocrmypdf/_logging.py
ocrmypdf/_metadata.py
ocrmypdf/_options.py
ocrmypdf/_pipeline.py
ocrmypdf/_plugin_manager.py
ocrmypdf/_plugin_registry.py
ocrmypdf/_progressbar.py
ocrmypdf/_validation.py
ocrmypdf/_validation_coordinator.py
ocrmypdf/_version.py
ocrmypdf/api.py
ocrmypdf/cli.py
ocrmypdf/exceptions.py
ocrmypdf/helpers.py
ocrmypdf/imageops.py
ocrmypdf/languages.py
ocrmypdf/optimize.py
ocrmypdf/pdfa.py
ocrmypdf/pluginspec.py
ocrmypdf/py.typed
ocrmypdf/quality.py
ocrmypdf/_exec/__init__.py
ocrmypdf/_exec/ghostscript.py
ocrmypdf/_exec/jbig2enc.py
ocrmypdf/_exec/pngquant.py
ocrmypdf/_exec/tesseract.py
ocrmypdf/_exec/unpaper.py
ocrmypdf/_exec/verapdf.py
ocrmypdf/_pipelines/__init__.py
ocrmypdf/_pipelines/_common.py
ocrmypdf/_pipelines/hocr_to_ocr_pdf.py
ocrmypdf/_pipelines/ocr.py
ocrmypdf/_pipelines/pdf_to_hocr.py
ocrmypdf/builtin_plugins/__init__.py
ocrmypdf/builtin_plugins/concurrency.py
ocrmypdf/builtin_plugins/default_filters.py
ocrmypdf/builtin_plugins/ghostscript.py
ocrmypdf/builtin_plugins/null_ocr.py
ocrmypdf/builtin_plugins/optimize.py
ocrmypdf/builtin_plugins/pypdfium.py
ocrmypdf/builtin_plugins/tesseract_ocr.py
ocrmypdf/data/NotoSans-Regular.ttf
ocrmypdf/data/Occulta.ttf
ocrmypdf/data/__init__.py
ocrmypdf/data/sRGB.icc
ocrmypdf/extra_plugins/__init__.py
ocrmypdf/extra_plugins/semfree.py
ocrmypdf/font/__init__.py
ocrmypdf/font/font_manager.py
ocrmypdf/font/font_provider.py
ocrmypdf/font/multi_font_manager.py
ocrmypdf/font/system_font_provider.py
ocrmypdf/fpdf_renderer/__init__.py
ocrmypdf/fpdf_renderer/renderer.py
ocrmypdf/hocrtransform/__init__.py
ocrmypdf/hocrtransform/__main__.py
ocrmypdf/hocrtransform/hocr_parser.py
ocrmypdf/models/__init__.py
ocrmypdf/models/ocr_element.py
ocrmypdf/pdfinfo/__init__.py
ocrmypdf/pdfinfo/_contentstream.py
ocrmypdf/pdfinfo/_image.py
ocrmypdf-17.1.0.dist-info/METADATA
ocrmypdf-17.1.0.dist-info/WHEEL
ocrmypdf-17.1.0.dist-info/entry_points.txt
ocrmypdf-17.1.0.dist-info/licenses/LICENSE
ocrmypdf-17.1.0.dist-info/RECORD
