Metadata-Version: 2.4
Name: ocrmypdf
Version: 17.1.0
Summary: OCRmyPDF adds an OCR text layer to scanned PDF files, allowing them to be searched
Project-URL: Documentation, https://ocrmypdf.readthedocs.io/
Project-URL: Source, https://github.com/ocrmypdf/OCRmyPDF
Project-URL: Tracker, https://github.com/ocrmypdf/OCRmyPDF/issues
Project-URL: Changelog, https://github.com/ocrmypdf/OCRmyPDF/docs/release_notes.md
Author-email: "James R. Barlow" <james@purplerock.ca>
License-Expression: MPL-2.0
License-File: LICENSE
Keywords: OCR,PDF,PDF/A,optical character recognition,scanning
Classifier: Development Status :: 5 - Production/Stable
Classifier: Environment :: Console
Classifier: Intended Audience :: End Users/Desktop
Classifier: Intended Audience :: Science/Research
Classifier: Intended Audience :: System Administrators
Classifier: Operating System :: MacOS
Classifier: Operating System :: Microsoft :: Windows
Classifier: Operating System :: POSIX
Classifier: Operating System :: POSIX :: BSD
Classifier: Operating System :: POSIX :: Linux
Classifier: Programming Language :: Python :: 3
Classifier: Topic :: Scientific/Engineering :: Image Recognition
Classifier: Topic :: Text Processing :: Indexing
Classifier: Topic :: Text Processing :: Linguistic
Requires-Python: >=3.11
Requires-Dist: deprecation>=2.1.0
Requires-Dist: fpdf2>=2.8.0
Requires-Dist: img2pdf>=0.5
Requires-Dist: packaging>=20
Requires-Dist: pdfminer-six>=20220319
Requires-Dist: pi-heif
Requires-Dist: pikepdf>=10
Requires-Dist: pillow>=10.0.1
Requires-Dist: pluggy>=1
Requires-Dist: pydantic>=2.12.5
Requires-Dist: pypdfium2>=5.0.0
Requires-Dist: rich>=13
Requires-Dist: uharfbuzz>=0.53.2
Provides-Extra: watcher
Requires-Dist: cyclopts>=3; extra == 'watcher'
Requires-Dist: python-dotenv; extra == 'watcher'
Requires-Dist: watchdog>=1.0.2; extra == 'watcher'
Provides-Extra: webservice
Requires-Dist: streamlit>=1.41.0; extra == 'webservice'
